pcib/__init__.py
pcib/core.py
pcib-1.0.dist-info/METADATA
pcib-1.0.dist-info/WHEEL
pcib-1.0.dist-info/entry_points.txt
pcib-1.0.dist-info/top_level.txt
pcib-1.0.dist-info/RECORD
