Metadata-Version: 2.1
Name: pcib
Version: 1.0
Summary: Python cURL-like library - аналог curl для Python
Home-page: UNKNOWN
Author: flamecode
License: UNKNOWN
Platform: UNKNOWN
Classifier: Programming Language :: Python :: 3
Classifier: License :: OSI Approved :: MIT License
Classifier: Operating System :: OS Independent
Requires-Python: >=3.6
Requires-Dist: requests (>=2.25.1)
